chope/__init__.py
chope/css.py
chope/element.py
chope/variable.py
chope/functions/__init__.py
chope/functions/color.py
chope/functions/function.py
chope/functions/shape.py
chope/functions/transform.py
chope-0.5.2.dist-info/LICENSE
chope-0.5.2.dist-info/METADATA
chope-0.5.2.dist-info/WHEEL
chope-0.5.2.dist-info/top_level.txt
chope-0.5.2.dist-info/RECORD
