Metadata-Version: 2.1
Name: chope
Version: 0.5.2
Summary: CSS & HTML on Python Easily
Author-email: Johan Tjuatja <hanstjua@yahoo.co.id>
Project-URL: Homepage, https://github.com/hanstjua/chope
Project-URL: Bug Tracker, https://github.com/hanstjua/chope/issues
Classifier: Programming Language :: Python :: 3.7
Classifier: Programming Language :: Python :: 3.8
Classifier: Programming Language :: Python :: 3.9
Classifier: Programming Language :: Python :: 3.10
Classifier: Programming Language :: Python :: 3.11
Classifier: License :: OSI Approved :: MIT License
Classifier: Operating System :: OS Independent
Requires-Python: >=3.7
License-File: LICENSE
Requires-Dist: pytest
